mongomancy/__init__.py
mongomancy/engine.py
mongomancy/mongo_errors.py
mongomancy/py.typed
mongomancy/schema.py
mongomancy/types.py
mongomancy-0.1.15.dist-info/LICENSE
mongomancy-0.1.15.dist-info/METADATA
mongomancy-0.1.15.dist-info/WHEEL
mongomancy-0.1.15.dist-info/top_level.txt
mongomancy-0.1.15.dist-info/RECORD
