Metadata-Version: 2.1
Name: mongomancy
Version: 0.1.15
Summary: Pymongo based python client with data definition layer.
Author-email: Tom Trval <thandeus@gmail.com>
License: GNU General Public License v3 (GPLv3)
Project-URL: Homepage, https://github.com/Ryu-CZ/mongomancy
Project-URL: Bug Tracker, https://github.com/Ryu-CZ/mongomancy/issues
Keywords: mongo,python,pymongo,database,nosql
Classifier: License :: OSI Approved :: GNU General Public License v3 (GPLv3)
Classifier: Operating System :: OS Independent
Classifier: Development Status :: 4 - Beta
Classifier: Intended Audience :: Developers
Classifier: Topic :: Database
Classifier: Programming Language :: Python :: 3
Classifier: Typing :: Typed
Requires-Python: >=3.10
License-File: LICENSE
Requires-Dist: pymongo >=4.0
